contex/analyze_regex.py
contex/__init__.py
contex-3.1.1.dist-info/RECORD
contex-3.1.1.dist-info/METADATA
contex-3.1.1.dist-info/WHEEL
contex-3.1.1.dist-info/metadata.json
contex-3.1.1.dist-info/top_level.txt
contex-3.1.1.dist-info/DESCRIPTION.rst
contex-3.1.1.dist-info/pbr.json
