Metadata-Version: 2.0
Name: contex
Version: 3.1.1
Summary: Contextual string manipulation
Home-page: https://notabug.org/Uglemat/Contex
Author: Mattias Ugelvik
Author-email: uglemat@gmail.com
License: GPL3+
Platform: UNKNOWN
Classifier: Topic :: Text Processing :: General
Classifier: License :: OSI Approved :: GNU General Public License v3 or later (GPLv3+)
Classifier: Programming Language :: Python :: 3
Classifier: Programming Language :: Python :: 2.7
Classifier: Intended Audience :: Developers
Classifier: Topic :: Software Development
